autora/runner/experimentation_manager/firebase/__init__.py
autora_runner_experimentation_manager_firebase-0.1.0.dist-info/METADATA
autora_runner_experimentation_manager_firebase-0.1.0.dist-info/WHEEL
autora_runner_experimentation_manager_firebase-0.1.0.dist-info/top_level.txt
autora_runner_experimentation_manager_firebase-0.1.0.dist-info/RECORD
