Metadata-Version: 2.1
Name: autora-runner-experimentation-manager-firebase
Version: 0.1.0
Summary: AutoRA Experimentation Manager Firebase provides functionality to manage communication of conditions and observation between AutoRA and an experiment on Firebase.
Author-email: Younes Strittmatter <younes_strittmatter@brown.edu>
License: MIT License
Project-URL: homepage, http://www.empiricalresearch.ai
Project-URL: repository, https://github.com/AutoResearch/autora-theorist-template
Project-URL: documentation, https://autoresearch.github.io/autora/
Requires-Python: <4,>=3.8
Requires-Dist: autora-core
Requires-Dist: firebase-admin
Provides-Extra: dev
Requires-Dist: autora-core[dev] ; extra == 'dev'
